pyrobopath/__init__.py
pyrobopath/collision_detection/__init__.py
pyrobopath/collision_detection/collision_model.py
pyrobopath/collision_detection/fcl_collision_models.py
pyrobopath/collision_detection/simple_collision_models.py
pyrobopath/collision_detection/trajectory.py
pyrobopath/collision_detection/trajectory_collision_detection.py
pyrobopath/process/__init__.py
pyrobopath/process/agent_model.py
pyrobopath/process/dependency_graph.py
pyrobopath/process/utilities.py
pyrobopath/scheduling/__init__.py
pyrobopath/scheduling/schedule.py
pyrobopath/scheduling/visualization.py
pyrobopath/toolpath/__init__.py
pyrobopath/toolpath/preprocessing.py
pyrobopath/toolpath/toolpath_core.py
pyrobopath/toolpath/path/__init__.py
pyrobopath/toolpath/path/path_core.py
pyrobopath/toolpath/path/smoothing.py
pyrobopath/toolpath/path/spline.py
pyrobopath/toolpath/path/transform.py
pyrobopath/toolpath/path/visualization.py
pyrobopath/toolpath/visualization/__init__.py
pyrobopath/toolpath/visualization/colors.py
pyrobopath/toolpath/visualization/matplotlib_backend.py
pyrobopath/toolpath/visualization/pyqtgraph_backend.py
pyrobopath/toolpath/visualization/visualizer.py
pyrobopath/toolpath_scheduling/__init__.py
pyrobopath/toolpath_scheduling/batched_planners.py
pyrobopath/toolpath_scheduling/depth_based_planners.py
pyrobopath/toolpath_scheduling/schedule.py
pyrobopath/toolpath_scheduling/toolpath_collision.py
pyrobopath/toolpath_scheduling/toolpath_scheduler.py
pyrobopath/toolpath_scheduling/visualization.py
pyrobopath/tools/__init__.py
pyrobopath/tools/_types_35.py
pyrobopath/tools/_types_39.py
pyrobopath/tools/geometry.py
pyrobopath/tools/linalg.py
pyrobopath/tools/types.py
pyrobopath/tools/utils.py
pyrobopath-0.2.8.dist-info/licenses/LICENSE
pyrobopath-0.2.8.dist-info/METADATA
pyrobopath-0.2.8.dist-info/WHEEL
pyrobopath-0.2.8.dist-info/top_level.txt
pyrobopath-0.2.8.dist-info/RECORD
