Metadata-Version: 2.4
Name: pyrobopath
Version: 0.2.8
Summary: This project contains python and ROS packages for working with robotic toolpaths
Author-email: Alex Arbogast <arbogastaw@gmail.com>
Project-URL: homepage, https://github.com/alexarbogast/pyrobopath
Project-URL: documentation, https://pyrobopath.readthedocs.io/en/latest/
Project-URL: issues, https://github.com/alexarbogast/pyrobopath/issues
Classifier: License :: OSI Approved :: MIT License
Classifier: Operating System :: OS Independent
Classifier: Programming Language :: Python :: 3.8
Classifier: Programming Language :: Python :: 3.9
Classifier: Programming Language :: Python :: 3.10
Classifier: Programming Language :: Python :: 3.11
Classifier: Programming Language :: Python :: 3.12
Requires-Python: >=3.8
License-File: LICENSE
Requires-Dist: matplotlib
Requires-Dist: networkx
Requires-Dist: gcodeparser
Requires-Dist: python-fcl
Requires-Dist: numpy>=1.21
Requires-Dist: numpy-quaternion
Requires-Dist: scipy
Requires-Dist: colorama
Requires-Dist: PyQt5
Requires-Dist: pyqtgraph
Requires-Dist: PyOpenGL
Provides-Extra: dev
Requires-Dist: pytest; extra == "dev"
Provides-Extra: docs
Requires-Dist: sphinx>=3.1; extra == "docs"
Requires-Dist: pydata-sphinx-theme; extra == "docs"
Requires-Dist: sphinx-copybutton; extra == "docs"
Dynamic: license-file
